flask_docs/__init__.py
flask_docs/static/css/style.css
flask_docs/static/fonts/FontAwesome.otf
flask_docs/static/fonts/fontawesome-webfont.eot
flask_docs/static/fonts/fontawesome-webfont.svg
flask_docs/static/fonts/fontawesome-webfont.ttf
flask_docs/static/fonts/fontawesome-webfont.woff
flask_docs/static/fonts/fontawesome-webfont.woff2
flask_docs/static/fonts/glyphicons-halflings-regular.eot
flask_docs/static/fonts/glyphicons-halflings-regular.svg
flask_docs/static/fonts/glyphicons-halflings-regular.ttf
flask_docs/static/fonts/glyphicons-halflings-regular.woff
flask_docs/static/fonts/glyphicons-halflings-regular.woff2
flask_docs/static/images/favicon.png
flask_docs/static/images/info.png
flask_docs/static/images/loading.gif
flask_docs/static/images/top.png
flask_docs/static/js/bootstrap.min.js
flask_docs/static/js/jquery-3.1.1.min.js
flask_docs/static/js/main.js
flask_docs/templates/flask_docs/base.html
flask_docs/templates/flask_docs/home.html
xt_FlaskAPIDocs-0.1.0.dist-info/LICENSE
xt_FlaskAPIDocs-0.1.0.dist-info/METADATA
xt_FlaskAPIDocs-0.1.0.dist-info/WHEEL
xt_FlaskAPIDocs-0.1.0.dist-info/top_level.txt
xt_FlaskAPIDocs-0.1.0.dist-info/RECORD
